Metadata-Version: 1.1
Name: aws-instance-debugger
Version: 0.5.3
Summary: CLI to debug AWS instances
Home-page: https://github.com/VivaReal/aws-instance-debugger/
Author: Marcos Araujo Sobrinho
Author-email: marcos.sobrinho@vivareal.com.br
License: MIT
Download-URL: https://pypi.python.org/pypi/aws-instance-debugger
Keywords: aws,boto3,ping,logs,processes,amazon web services
Platform: UNKNOWN
